neurovc/__init__.py
neurovc/_version.py
neurovc/cameras/__init__.py
neurovc/contrib/__init__.py
neurovc/contrib/flowmag/LICENSE
neurovc/contrib/flowmag/__init__.py
neurovc/contrib/flowmag/dataset.py
neurovc/contrib/flowmag/eval.py
neurovc/contrib/flowmag/flow_utils.py
neurovc/contrib/flowmag/inference.py
neurovc/contrib/flowmag/losses.py
neurovc/contrib/flowmag/metrics.py
neurovc/contrib/flowmag/model.py
neurovc/contrib/flowmag/myutils.py
neurovc/contrib/flowmag/test_time_adapt.py
neurovc/contrib/flowmag/train.py
neurovc/contrib/flowmag/configs/alpha16.color10.arflow.yaml
neurovc/contrib/flowmag/configs/alpha16.color10.yaml
neurovc/contrib/flowmag/flow_models/ARFlow/.gitignore
neurovc/contrib/flowmag/flow_models/ARFlow/Dockerfile
neurovc/contrib/flowmag/flow_models/ARFlow/LICENSE
neurovc/contrib/flowmag/flow_models/ARFlow/README.md
neurovc/contrib/flowmag/flow_models/ARFlow/basic_train.py
neurovc/contrib/flowmag/flow_models/ARFlow/inference.py
neurovc/contrib/flowmag/flow_models/ARFlow/logger.py
neurovc/contrib/flowmag/flow_models/ARFlow/requirements.txt
neurovc/contrib/flowmag/flow_models/ARFlow/train.py
neurovc/contrib/flowmag/flow_models/ARFlow/configs/kitti15_ft.json
neurovc/contrib/flowmag/flow_models/ARFlow/configs/kitti15_ft_ar.json
neurovc/contrib/flowmag/flow_models/ARFlow/configs/kitti_raw.json
neurovc/contrib/flowmag/flow_models/ARFlow/configs/sintel_ft.json
neurovc/contrib/flowmag/flow_models/ARFlow/configs/sintel_ft_ar.json
neurovc/contrib/flowmag/flow_models/ARFlow/configs/sintel_raw.json
neurovc/contrib/flowmag/flow_models/ARFlow/losses/flow_loss.py
neurovc/contrib/flowmag/flow_models/ARFlow/losses/get_loss.py
neurovc/contrib/flowmag/flow_models/ARFlow/losses/loss_blocks.py
neurovc/contrib/flowmag/flow_models/ARFlow/models/correlation_native.py
neurovc/contrib/flowmag/flow_models/ARFlow/models/get_model.py
neurovc/contrib/flowmag/flow_models/ARFlow/models/pwclite.py
neurovc/contrib/flowmag/flow_models/ARFlow/models/correlation_package/__init__.py
neurovc-0.1.1.dist-info/licenses/LICENSE
neurovc-0.1.1.dist-info/METADATA
neurovc-0.1.1.dist-info/WHEEL
neurovc-0.1.1.dist-info/top_level.txt
neurovc-0.1.1.dist-info/RECORD
