Metadata-Version: 2.4
Name: neurovc
Version: 0.1.1
Summary: Framework for Computer Vision setups in Neuroscience
Author-email: Philipp Flotho <Philipp.Flotho@uni-saarland.de>
License: CC BY-NC-SA 4.0
Classifier: Development Status :: 5 - Production/Stable
Classifier: Intended Audience :: Science/Research
Classifier: License :: Other/Proprietary License
Classifier: Operating System :: OS Independent
Classifier: Programming Language :: Python :: 3
Classifier: Programming Language :: Python :: 3.10
Classifier: Programming Language :: Python :: 3.11
Classifier: Programming Language :: Python :: 3.12
Classifier: Topic :: Scientific/Engineering :: Artificial Intelligence
Classifier: Topic :: Multimedia :: Video
Classifier: Topic :: Scientific/Engineering :: Image Processing
Classifier: Topic :: Scientific/Engineering :: Image Recognition
Requires-Python: <3.13,>=3.10
License-File: LICENSE
Requires-Dist: numpy>=1.24.0
Requires-Dist: opencv-contrib-python>=4.10.0
Provides-Extra: contrib
Requires-Dist: configobj>=5.0.8; extra == "contrib"
Requires-Dist: dominate>=2.7.0; extra == "contrib"
Requires-Dist: easydict>=1.10.0; extra == "contrib"
Requires-Dist: einops>=0.4.1; extra == "contrib"
Requires-Dist: gdown>=4.7.1; extra == "contrib"
Requires-Dist: matplotlib>=3.5.0; extra == "contrib"
Requires-Dist: omegaconf>=2.3.0; extra == "contrib"
Requires-Dist: tensorboard>=2.11.2; extra == "contrib"
Requires-Dist: torch>=2.0.0; extra == "contrib"
Requires-Dist: torchvision>=0.15.0; extra == "contrib"
Requires-Dist: Pillow>=10.2.0; extra == "contrib"
Provides-Extra: landmark
Requires-Dist: yolov5-face>=0.0.2; extra == "landmark"
Requires-Dist: gdown>=5.2.0; extra == "landmark"
Provides-Extra: momag
Requires-Dist: moderngl>=5.12.0; extra == "momag"
Requires-Dist: mediapipe>=0.10.0; extra == "momag"
Requires-Dist: scipy>=1.10.0; extra == "momag"
Requires-Dist: numba>=0.58.0; extra == "momag"
Requires-Dist: h5py>=3.11.0; extra == "momag"
Provides-Extra: test
Requires-Dist: pytest>=8.0.0; extra == "test"
Requires-Dist: pytest-cov>=5.0.0; extra == "test"
Dynamic: license-file
